[
    {
        "name": "stripe",
        "type": "service",
        "urls": [
            "https://api.stripe.com",
            "https://js.stripe.com"
        ],
        "packages": [
            {
                "name": "github.com/stripe/stripe-go",
                "manager": "go"
            },
            {
                "name": "stripe",
                "manager": "rubygems"
            }
        ]
    },
    {
        "name": "postgres",
        "type": "data_store",
        "urls": [],
        "packages": [
            {
                "name": "pg",
                "manager": "rubygems"
            }
        ]
    }
]